calypr_admin/__init__.py
calypr_admin/config.yaml
calypr_admin/admin/__init__.py
calypr_admin/admin/cli.py
calypr_admin/admin/collaborator/__init__.py
calypr_admin/admin/collaborator/cli.py
calypr_admin/admin/collaborator/access/__init__.py
calypr_admin/admin/collaborator/access/requestor.py
calypr_admin/admin/collaborator/access/policies/__init__.py
calypr_admin/admin/collaborator/access/policies/add-project-default.yaml
calypr_admin/admin/collaborator/access/policies/add-user-read.yaml
calypr_admin/admin/collaborator/access/policies/add-user-write.yaml
calypr_admin/admin/gen3/__init__.py
calypr_admin/admin/gen3/buckets/__init__.py
calypr_admin/admin/gen3/buckets/cli.py
calypr_admin/admin/gen3/buckets/lister.py
calypr_admin/admin/projects/__init__.py
calypr_admin/admin/projects/adder.py
calypr_admin/admin/projects/cli.py
calypr_admin/admin/projects/lister.py
calypr_admin/admin/projects/remover.py
calypr_admin/common/__init__.py
calypr_admin/config/__init__.py
calypr_admin-0.0.2.dist-info/licenses/LICENSE
calypr_admin-0.0.2.dist-info/METADATA
calypr_admin-0.0.2.dist-info/WHEEL
calypr_admin-0.0.2.dist-info/entry_points.txt
calypr_admin-0.0.2.dist-info/top_level.txt
calypr_admin-0.0.2.dist-info/RECORD
